realtimex_docs_server/__init__.py
realtimex_docs_server/__main__.py
realtimex_docs_server/server.py
realtimex_docs_server/docs/workflows/evn_invoice_download.md
realtimex_docs_server/docs/workflows/fpt_invoice_download.md
realtimex_docs_server-0.1.3.dist-info/METADATA
realtimex_docs_server-0.1.3.dist-info/WHEEL
realtimex_docs_server-0.1.3.dist-info/entry_points.txt
realtimex_docs_server-0.1.3.dist-info/licenses/LICENSE
realtimex_docs_server-0.1.3.dist-info/RECORD
