Metadata-Version: 2.4
Name: realtimex-docs-server
Version: 0.1.3
Summary: MCP server that exposes local documentation to agents
Author: RealTimeX
License-Expression: MIT
License-File: LICENSE
Keywords: automation,documentation,fastmcp,mcp
Requires-Python: >=3.10
Requires-Dist: fastmcp>=2.13.0.2
Requires-Dist: pydantic>=2.12.4
